tagsimplify/__init__.py
tagsimplify-1.0.0.dist-info/LICENSE.txt
tagsimplify-1.0.0.dist-info/METADATA
tagsimplify-1.0.0.dist-info/WHEEL
tagsimplify-1.0.0.dist-info/top_level.txt
tagsimplify-1.0.0.dist-info/RECORD
