Metadata-Version: 2.1
Name: tagsimplify
Version: 1.0.0
Summary: It simplifies the tags
Home-page: https://github.com/bhuvneshsaini/tagsimplify
Author: Bhuvnesh Saini
Author-email: bhuvneshsaini5@gmail.com
License: MIT
Platform: UNKNOWN
Classifier: License :: OSI Approved :: MIT License
Classifier: Programming Language :: Python :: 3.6
Classifier: Programming Language :: Python :: 3.7
Classifier: Programming Language :: Python :: 3.8
Requires-Dist: regex
